jsfiddle_readme/__init__.py
jsfiddle_readme/__main__.py
jsfiddle_readme-2019.4.8.dist-info/METADATA
jsfiddle_readme-2019.4.8.dist-info/WHEEL
jsfiddle_readme-2019.4.8.dist-info/top_level.txt
jsfiddle_readme-2019.4.8.dist-info/RECORD
