Metadata-Version: 2.1
Name: jsfiddle-readme
Version: 2019.4.8
Summary: generate jsfiddle README.md
Home-page: https://github.com/looking-for-a-job/jsfiddle-readme.py
License: UNKNOWN
Keywords: jsfiddle
Platform: UNKNOWN
Classifier: Operating System :: OS Independent
Classifier: Programming Language :: Python
Classifier: Programming Language :: Python :: 2
Classifier: Programming Language :: Python :: 2.7
Classifier: Programming Language :: Python :: 3
Classifier: Programming Language :: Python :: 3.4
Classifier: Programming Language :: Python :: 3.5
Classifier: Programming Language :: Python :: 3.6
Classifier: Topic :: Documentation
Requires-Dist: click
Requires-Dist: jsfiddle
Requires-Dist: markdown-table
Requires-Dist: public
Requires-Dist: setuptools
